packageManager/__init__.py
packageManager/manager.py
package_manager_TirsvadCLI-0.1.12.dist-info/LICENSE
package_manager_TirsvadCLI-0.1.12.dist-info/METADATA
package_manager_TirsvadCLI-0.1.12.dist-info/WHEEL
package_manager_TirsvadCLI-0.1.12.dist-info/top_level.txt
package_manager_TirsvadCLI-0.1.12.dist-info/RECORD
