Metadata-Version: 2.1
Name: package-manager-TirsvadCLI
Version: 0.1.12
Summary: UNKNOWN
Home-page: https://github.com/orgs/Tirsvad-CLI-Tools/
Author: Jens Tirsvad Nielsen
Author-email: jenstirsvad@gmail.com
License: UNKNOWN
Platform: UNKNOWN
Classifier: License :: OSI Approved :: GNU Affero General Public License v3 or later (AGPLv3+)
Classifier: Programming Language :: Python :: 3
Classifier: Programming Language :: Python :: 3.6
Classifier: Programming Language :: Python :: 3.7
Classifier: Programming Language :: Python :: 3.8
Classifier: Environment :: Console
Classifier: Operating System :: POSIX :: Linux
Classifier: Topic :: Software Development :: Libraries :: Python Modules
Requires-Python: >=3.6, <4
Requires-Dist: distro
Provides-Extra: test
Requires-Dist: coverage ; extra == 'test'
Requires-Dist: pytest ; extra == 'test'
Requires-Dist: pytest-cov ; extra == 'test'
Requires-Dist: coveralls ; extra == 'test'
Requires-Dist: PyYAML ; extra == 'test'
